sktools/__init__.py
sktools/encoders.py
sktools/ensemble.py
sktools/imputer.py
sktools/linear_model.py
sktools/matrix_denser.py
sktools/model_selection.py
sktools/preprocessing.py
sktools/quantilegroups.py
sktools/selectors.py
sktools-0.1.4.dist-info/AUTHORS.rst
sktools-0.1.4.dist-info/LICENSE
sktools-0.1.4.dist-info/METADATA
sktools-0.1.4.dist-info/WHEEL
sktools-0.1.4.dist-info/top_level.txt
sktools-0.1.4.dist-info/RECORD
