Metadata-Version: 2.1
Name: sktools
Version: 0.1.4
Summary: Tools to extend sklearn
Home-page: https://github.com/david26694/sktools
Author: David Masip Bonet
Author-email: david26694@gmail.com
License: MIT license
Keywords: sktools
Platform: UNKNOWN
Classifier: Development Status :: 2 - Pre-Alpha
Classifier: Intended Audience :: Developers
Classifier: License :: OSI Approved :: MIT License
Classifier: Natural Language :: English
Classifier: Programming Language :: Python :: 3
Classifier: Programming Language :: Python :: 3.5
Classifier: Programming Language :: Python :: 3.6
Classifier: Programming Language :: Python :: 3.7
Classifier: Programming Language :: Python :: 3.8
Requires-Python: >=3.5
Requires-Dist: scikit-learn
Requires-Dist: pandas
Requires-Dist: scipy
Requires-Dist: numpy
Requires-Dist: category-encoders
Requires-Dist: statsmodels
